{
    "id": "1500246820922855444",
    "username": "s1rk4",
    "avatar": "ddb5a09b15eb66e8e89f62de7c1b6543",
    "discriminator": "0",
    "public_flags": 0,
    "flags": 0,
    "banner": null,
    "accent_color": null,
    "global_name": "!                          S1RK4",
    "avatar_decoration_data": null,
    "collectibles": null,
    "display_name_styles": null,
    "banner_color": null,
    "clan": null,
    "primary_guild": null,
    "mfa_enabled": false,
    "locale": "fr",
    "premium_type": 0,
    "email": "contact.ravendev@gmail.com",
    "verified": true,
    "phone": null,
    "nsfw_allowed": true,
    "linked_users": [],
    "bio": "",
    "authenticator_types": [],
    "age_verification_status": 1,
    "2fa_advanced": {
        "mfa_enabled": false,
        "level": "Élevé",
        "method": "Discord Authenticator + SMS",
        "backup_codes": false,
        "phone_verified": false
    }
}